odoo/addons/sale_limit_partner_address/__init__.py
odoo/addons/sale_limit_partner_address/__manifest__.py
odoo/addons/sale_limit_partner_address/views/sale_order_view.xml
odoo14_addon_sale_limit_partner_address-14.0.0.0.1.dist-info/METADATA
odoo14_addon_sale_limit_partner_address-14.0.0.0.1.dist-info/WHEEL
odoo14_addon_sale_limit_partner_address-14.0.0.0.1.dist-info/top_level.txt
odoo14_addon_sale_limit_partner_address-14.0.0.0.1.dist-info/RECORD
